objtreexml/__init__.py
objtreexml/objtreexml.py
objtreexml/test.py
objtreexml-0.0.1.dist-info/LICENSE
objtreexml-0.0.1.dist-info/METADATA
objtreexml-0.0.1.dist-info/WHEEL
objtreexml-0.0.1.dist-info/top_level.txt
objtreexml-0.0.1.dist-info/RECORD
