Metadata-Version: 2.1
Name: objtreexml
Version: 0.0.1
Summary: A package to convert object trees to xml and back
Home-page: https://github.com/aver007/obj-tree-to-xml
Author: a.v.e.r
Author-email: a.v.e.r@mail.ru
License: UNKNOWN
Platform: UNKNOWN
Classifier: Programming Language :: Python :: 3.8
Classifier: License :: OSI Approved :: GNU General Public License v3 (GPLv3)
Requires-Dist: xmljson
